komplot/__init__.py
komplot/_contour.py
komplot/_event.py
komplot/_imview.py
komplot/_ipython.py
komplot/_misc.py
komplot/_plot.py
komplot/_state.py
komplot/_surface.py
komplot/_version.py
komplot/_volview.py
komplot-0.0.1.dist-info/licenses/LICENSE
komplot-0.0.1.dist-info/METADATA
komplot-0.0.1.dist-info/WHEEL
komplot-0.0.1.dist-info/top_level.txt
komplot-0.0.1.dist-info/RECORD
