Metadata-Version: 2.4
Name: komplot
Version: 0.0.1
Summary: Simplified matplotlib interface
Author-email: Brendt Wohlberg <brendt@ieee.org>
License: BSD 3-Clause License
Project-URL: homepage, https://komplot.readthedocs.io
Project-URL: source, https://github.com/bwohlberg/komplot
Keywords: plotting
Classifier: Programming Language :: Python :: 3
Classifier: License :: OSI Approved :: BSD License
Classifier: Operating System :: OS Independent
Classifier: Intended Audience :: Developers
Classifier: Topic :: Utilities
Requires-Python: >=3.9
License-File: LICENSE
Requires-Dist: matplotlib
Requires-Dist: numpy
Provides-Extra: examples
Requires-Dist: imageio; extra == "examples"
Requires-Dist: ipympl; extra == "examples"
Provides-Extra: docs
Requires-Dist: imageio; extra == "docs"
Requires-Dist: ipympl; extra == "docs"
Requires-Dist: sphinx; extra == "docs"
Requires-Dist: furo; extra == "docs"
Requires-Dist: sphinxcontrib-napoleon; extra == "docs"
Requires-Dist: sphinx-autodoc-typehints; extra == "docs"
Requires-Dist: toml; extra == "docs"
Requires-Dist: nbsphinx; extra == "docs"
Requires-Dist: ipython; extra == "docs"
Requires-Dist: ipykernel; extra == "docs"
Dynamic: license-file
